[
  {
    "id": "learn-coding",
    "title": "如何学习编程（也许不学也行?）",
    "summary": "一堆犯错与踩坑后的随感：节奏、动机、反馈闭环，还有放弃恐惧。",
    "date": "2025-02-10",
    "category": "学习",
    "tags": ["Learning","Mindset"],
    "url": "#",
    "lang": "zh"
  },
  {
    "id": "frontend-ai-flow",
    "title": "前端开发技巧：AI 辅助下的最小工作流",
    "summary": "把注意力留给信息架构与交互，重复劳动交给工具链。",
    "date": "2025-02-11",
    "category": "前端",
    "tags": ["Frontend","AI"],
    "url": "#",
    "lang": "zh"
  },
  {
    "id": "stack-reflection",
    "title": "我的技术栈（其实没有）",
    "summary": "堆栈是一种动态分布，不是身份标签。",
    "date": "2025-02-12",
    "category": "随笔",
    "tags": ["Reflection"],
    "url": "#",
    "lang": "zh"
  },
  {
    "id": "game-moments",
    "title": "游戏相关：那些好玩的瞬间",
    "summary": "碎片时间里的体验与机制观察。",
    "date": "2025-02-13",
    "category": "游戏",
    "tags": ["Game"],
    "url": "/blog/game/index.html",
    "lang": "zh"
  }
]
